sqlalchemy_redshift/__init__.py
sqlalchemy_redshift/commands.py
sqlalchemy_redshift/ddl.py
sqlalchemy_redshift/dialect.py
sqlalchemy_redshift/redshift-ca-bundle.crt
deepnote_sqlalchemy_redshift-0.8.17.dist-info/METADATA
deepnote_sqlalchemy_redshift-0.8.17.dist-info/WHEEL
deepnote_sqlalchemy_redshift-0.8.17.dist-info/entry_points.txt
deepnote_sqlalchemy_redshift-0.8.17.dist-info/licenses/LICENSE
deepnote_sqlalchemy_redshift-0.8.17.dist-info/RECORD
