Metadata-Version: 2.4
Name: deepnote-sqlalchemy-redshift
Version: 0.8.17
Summary: Amazon Redshift Dialect for sqlalchemy
Project-URL: Homepage, https://github.com/deepnote/sqlalchemy-redshift
Author-email: Matt George <mgeorge@gmail.com>
Maintainer-email: Deepnote <product-engineers@deepnote.com>
License-Expression: MIT
License-File: LICENSE
Classifier: Development Status :: 4 - Beta
Classifier: Environment :: Console
Classifier: Intended Audience :: Developers
Classifier: Operating System :: OS Independent
Classifier: Programming Language :: Python
Classifier: Programming Language :: Python :: 3
Classifier: Programming Language :: Python :: 3.9
Classifier: Programming Language :: Python :: 3.10
Classifier: Programming Language :: Python :: 3.11
Classifier: Programming Language :: Python :: 3.12
Classifier: Programming Language :: Python :: 3.13
Requires-Python: <3.14,>=3.9
Requires-Dist: packaging
Requires-Dist: sqlalchemy<3.0.0,>=1.4.15
